{
   "format_version": "1.8.0",
   "minecraft:entity": {
      "description": {
         "identifier": "cosmos:rocket_tier_1",
         "is_summonable": true,
         "properties": {
                "cosmos:rotation_x": {
                  "type": "float",
                  "range": [0.0, 180.0],
                  "default": 90.0,
                  "client_sync": true
                }
            }
      },
        "component_groups": {
         "inv0": {
            "minecraft:inventory": {
               "container_type": "chest_boat",
               "inventory_size": 2
            }
         },
			"inv18": {
            "minecraft:inventory": {
               "container_type": "chest_boat",
               "inventory_size": 20
            }
			},
			"inv36": {
            "minecraft:inventory": {
               "container_type": "chest_boat",
               "inventory_size": 38
            }
			},
			"inv54": {
            "minecraft:inventory": {
               "container_type": "chest_boat",
               "inventory_size": 56
            }
			}
   },
      "components": {       
         "minecraft:collision_box": {
            "height": 4,
            "width": 1
         },
         "minecraft:fall_damage": {
            "value": 0
         },
         "minecraft:fire_immune": true,
         "minecraft:health": {
            "max": 1,
            "value": 1
         },
         "minecraft:knockback_resistance": {
            "value": 1
         },
         "minecraft:push_through": {
            "value": 1
         },
         "minecraft:pushable": {
            "is_pushable": false,
            "is_pushable_by_piston": false
         },
         "minecraft:physics": {
            "has_gravity": true,
            "has_collision": true
         },
         "minecraft:rideable": {
            "crouching_skip_interact": true,
            "family_types": [
               "player",
               "Rider"
            ],
            "interact_text": "Ride",
            "priority": 0,
            "pull_in_entities": false,
            "seat_count": 1,
            "seats": {
               "position": [0, 0.3, 0]
            }
         },
         "minecraft:type_family": {
            "family": [
               "rocket",
               "vehicle"
            ]
         }
      },
      "events": {
         "cosmos:tick": {
             "queue_command": {
                  "command": "scriptevent cosmos:rocket tick"
            }
         },
         "cosmos:inv0": {
                "add":{
                    "component_groups": ["inv0"]
            }
         },
         "cosmos:inv18": {
                "add":{
                    "component_groups": ["inv18"]
            }
         },
         "cosmos:inv36": {
                "add":{
                    "component_groups": ["inv36"]
            }
         },
         "cosmos:inv54": {
                "add":{
                    "component_groups": ["inv54"]
            }
         }
      }
   }
}
